repwatcher/__init__.py
repwatcher/__main__.py
repwatcher/cli.py
repwatcher/config.py
repwatcher/db.py
repwatcher/gui.py
repwatcher/models.py
repwatcher/replay.py
repwatcher/watcher.py
repwatcher/webclient.py
repwatcher-0.2.1.dist-info/LICENSE
repwatcher-0.2.1.dist-info/METADATA
repwatcher-0.2.1.dist-info/WHEEL
repwatcher-0.2.1.dist-info/entry_points.txt
repwatcher-0.2.1.dist-info/top_level.txt
repwatcher-0.2.1.dist-info/RECORD
