Metadata-Version: 2.1
Name: repwatcher
Version: 0.2.1
Summary: Tool to automatically upload SC:BW replays to RepMastered.com
Author-email: Thomas McManus <mcmanustfj@gmail.com>
Maintainer-email: Thomas McManus <mcmanustfj@gmail.com>
License: MIT license
Project-URL: bugs, https://github.com/mcmanustfj/repwatcher/issues
Project-URL: changelog, https://github.com/mcmanustfj/repwatcher/blob/master/CHANGELOG.md
Project-URL: homepage, https://github.com/mcmanustfj/repwatcher
Keywords: starcraft,replays,repmastered
Requires-Python: >=3.8
License-File: LICENSE
Requires-Dist: requests
Requires-Dist: platformdirs
Requires-Dist: watchdog
Requires-Dist: rich
Requires-Dist: typer
Requires-Dist: peewee>=3.17.8
Requires-Dist: beautifulsoup4>=4.12.3
Requires-Dist: ttkbootstrap>=1.10.1
Provides-Extra: dev
Requires-Dist: pyright; extra == "dev"
Requires-Dist: ruff; extra == "dev"
Requires-Dist: build; extra == "dev"
Requires-Dist: twine; extra == "dev"
